supersonic/__init__.py
supersonic/cli.py
supersonic/core/__init__.py
supersonic/core/config.py
supersonic/core/diff.py
supersonic/core/errors.py
supersonic/core/github.py
supersonic/core/pr.py
supersonic/tests/__init__.py
supersonic/tests/test_cli.py
supersonic/tests/test_config.py
supersonic/tests/test_git.py
supersonic/tests/test_github.py
supersonic/tests/test_pr.py
supersonic/utils/__init__.py
supersonic/utils/git.py
supersonic-0.2.4.dist-info/METADATA
supersonic-0.2.4.dist-info/WHEEL
supersonic-0.2.4.dist-info/entry_points.txt
supersonic-0.2.4.dist-info/licenses/LICENSE
supersonic-0.2.4.dist-info/RECORD
