Metadata-Version: 2.4
Name: supersonic
Version: 0.2.4
Summary: GitHub PR automation for modern applications
Author-email: Cased <ted@cased.com>
License-Expression: MIT
License-File: LICENSE
Requires-Python: >=3.11
Requires-Dist: click<9.0.0,>=8.1.3
Requires-Dist: gitpython<4.0.0,>=3.1.40
Requires-Dist: jinja2<4.0.0,>=3.1.2
Requires-Dist: pydantic<3.0.0,>=2.0.0
Requires-Dist: pygithub<3.0.0,>=2.1.1
Requires-Dist: requests<3.0.0,>=2.31.0
Requires-Dist: types-requests<3.0.0,>=2.31.0
Provides-Extra: dev
Requires-Dist: mypy<2.0.0,>=1.5.1; extra == 'dev'
Requires-Dist: pytest-cov<5.0.0,>=4.1.0; extra == 'dev'
Requires-Dist: pytest-mypy<0.11.0,>=0.10.3; extra == 'dev'
Requires-Dist: pytest<8.0.0,>=7.4.0; extra == 'dev'
Requires-Dist: ruff<0.2.0,>=0.1.9; extra == 'dev'
Requires-Dist: types-click<8.0.0,>=7.1.8; extra == 'dev'
